jwql/__init__.py
jwql/example_config.json
jwql/install-env.sh
jwql/pull_jwql_branch.sh
jwql/database/__init__.py
jwql/database/clone_tables.py
jwql/database/database_interface.py
jwql/database/reset_database.py
jwql/database/monitor_table_definitions/fgs/fgs_bad_pixel_query_history.txt
jwql/database/monitor_table_definitions/fgs/fgs_bad_pixel_stats.txt
jwql/database/monitor_table_definitions/fgs/fgs_cosmic_ray_query_history.txt
jwql/database/monitor_table_definitions/fgs/fgs_cosmic_ray_stats.txt
jwql/database/monitor_table_definitions/fgs/fgs_dark_dark_current.txt
jwql/database/monitor_table_definitions/fgs/fgs_dark_pixel_stats.txt
jwql/database/monitor_table_definitions/fgs/fgs_dark_query_history.txt
jwql/database/monitor_table_definitions/fgs/fgs_edb_blocks_stats.txt
jwql/database/monitor_table_definitions/fgs/fgs_edb_daily_stats.txt
jwql/database/monitor_table_definitions/fgs/fgs_edb_every_change_stats.txt
jwql/database/monitor_table_definitions/fgs/fgs_edb_mnemonics.txt
jwql/database/monitor_table_definitions/fgs/fgs_edb_time_interval_stats.txt
jwql/database/monitor_table_definitions/fgs/fgs_readnoise_query_history.txt
jwql/database/monitor_table_definitions/fgs/fgs_readnoise_stats.txt
jwql/database/monitor_table_definitions/miri/miri_bad_pixel_query_history.txt
jwql/database/monitor_table_definitions/miri/miri_bad_pixel_stats.txt
jwql/database/monitor_table_definitions/miri/miri_cosmic_ray_query_history.txt
jwql/database/monitor_table_definitions/miri/miri_cosmic_ray_stats.txt
jwql/database/monitor_table_definitions/miri/miri_dark_dark_current.txt
jwql/database/monitor_table_definitions/miri/miri_dark_pixel_stats.txt
jwql/database/monitor_table_definitions/miri/miri_dark_query_history.txt
jwql/database/monitor_table_definitions/miri/miri_edb_blocks_stats.txt
jwql/database/monitor_table_definitions/miri/miri_edb_daily_stats.txt
jwql/database/monitor_table_definitions/miri/miri_edb_every_change_stats.txt
jwql-1.4.1.dist-info/licenses/LICENSE
jwql-1.4.1.dist-info/METADATA
jwql-1.4.1.dist-info/WHEEL
jwql-1.4.1.dist-info/top_level.txt
jwql-1.4.1.dist-info/RECORD
