Metadata-Version: 2.4
Name: jwql
Version: 1.4.1
Summary: The James Webb Space Telescope Quicklook Project
Author: Matthew Bourque, Lauren Chambers, Misty Cracraft, Mike Engesser, Mees Fix, Joe Filippazzo, Bryan Hilbert
License: Copyright (c) 2017, AURA
Keywords: astronomy,python
Classifier: Programming Language :: Python
Requires-Python: >=3.10
License-File: LICENSE
Requires-Dist: asdf<4,>=3.1.0
Requires-Dist: astropy<7,>=6.0
Requires-Dist: astroquery<0.5.0,>=0.4.7
Requires-Dist: beautifulsoup4<5,>=4.12.3
Requires-Dist: bokeh<4,>=3.4.0
Requires-Dist: celery<6,>=5.3.6
Requires-Dist: crds<12,>=11.17.19
Requires-Dist: django<6,>=5.0.3
Requires-Dist: gunicorn<23.0.0,>=22.0.0
Requires-Dist: inflection<0.6,>=0.5.1
Requires-Dist: jsonschema<5,>=4.21.1
Requires-Dist: jwst<2,>=1.13.4
Requires-Dist: jwst_backgrounds<1.3.0,>=1.2.0
Requires-Dist: jwst_reffiles>=1.0.1
Requires-Dist: matplotlib<4,>=3.8.3
Requires-Dist: numpy<2,>=1.26.4
Requires-Dist: pandas<3,>=2.2.1
Requires-Dist: psycopg2-binary<3,>=2.9.9
Requires-Dist: pysiaf>=0.22.0
Requires-Dist: pyvo<2,>=1.5.1
Requires-Dist: redis<6,>=5.0.3
Requires-Dist: scipy<2,>=1.12.0
Requires-Dist: selenium<5,>=4.18.1
Requires-Dist: sqlalchemy<3,>=2.0.29
Requires-Dist: torch<2.5.2,>=2.2.2
Requires-Dist: torchvision<0.20.2,>=0.17.2
Requires-Dist: wtforms<4,>=3.1.2
Provides-Extra: test
Requires-Dist: pytest>=9.0; extra == "test"
Requires-Dist: pytest-cov; extra == "test"
Requires-Dist: pytest-mock; extra == "test"
Provides-Extra: docs
Requires-Dist: numpydoc; extra == "docs"
Requires-Dist: sphinx; extra == "docs"
Requires-Dist: sphinx_rtd_theme; extra == "docs"
Requires-Dist: stsci_rtd_theme; extra == "docs"
Requires-Dist: sphinx_automodapi; extra == "docs"
Dynamic: license-file
